edxml/__init__.py
edxml/error.py
edxml/event.py
edxml/event.pyi
edxml/event_collection.py
edxml/event_validator.py
edxml/filter.py
edxml/filter.pyi
edxml/logger.py
edxml/parser.py
edxml/parser.pyi
edxml/template.py
edxml/util.py
edxml/version.py
edxml/writer.py
edxml/cli/__init__.py
edxml/cli/edxml_cat.py
edxml/cli/edxml_ddgen.py
edxml/cli/edxml_diff.py
edxml/cli/edxml_filter.py
edxml/cli/edxml_hash.py
edxml/cli/edxml_merge.py
edxml/cli/edxml_mine.py
edxml/cli/edxml_replay.py
edxml/cli/edxml_stats.py
edxml/cli/edxml_template_tester.py
edxml/cli/edxml_to_delimited.py
edxml/cli/edxml_to_text.py
edxml/cli/edxml_validate.py
edxml/examples/__init__.py
edxml/examples/brick_register.py
edxml/examples/define_parent_declarative.py
edxml/examples/event_collection.py
edxml/examples/event_representation_attachments_dict.py
edxml/examples/event_representation_properties_dict_read.py
edxml/examples/event_representation_properties_dict_write.py
edxml/examples/event_type_factory.py
edxml/examples/event_writer.py
edxml/examples/mining_knowledge_base.py
edxml/examples/parser_pull.py
edxml/examples/transcoder_harness.py
edxml/examples/transcoder_object.py
edxml/examples/transcoder_object_mediator.py
edxml/examples/transcoder_xml_mediator.py
edxml/miner/__init__.py
edxml/miner/inference.py
edxml/miner/knowledge.py
edxml/miner/miner.py
edxml/miner/node.py
edxml/miner/parser.py
edxml/miner/result.py
edxml/miner/graph/__init__.py
edxml/miner/graph/construct.py
edxml/miner/graph/graph.py
edxml/miner/graph/visualize.py
edxml/ontology/__init__.py
edxml/ontology/brick.py
edxml/ontology/brick.pyi
edxml/ontology/concept.py
edxml/ontology/concept.pyi
edxml/ontology/data_type.py
edxml/ontology/data_type.pyi
edxml/ontology/description.py
edxml/ontology/event_property.py
edxml/ontology/event_property.pyi
edxml/ontology/event_property_concept.py
edxml/ontology/event_property_concept.pyi
edxml/ontology/event_property_relation.py
edxml/ontology/event_property_relation.pyi
edxml-3.0.1.dist-info/LICENSE.rst
edxml-3.0.1.dist-info/METADATA
edxml-3.0.1.dist-info/WHEEL
edxml-3.0.1.dist-info/entry_points.txt
edxml-3.0.1.dist-info/top_level.txt
edxml-3.0.1.dist-info/RECORD
